<?xml version="1.0" encoding="utf-8" ?>
<dwsync>
<file name="book.png" server="mayan-capital.com" local="130055691460000000" remote="131326317000000000" Dst="1" />
<file name="cabinet.png" server="mayan-capital.com" local="130055691460000000" remote="131326317000000000" Dst="1" />
<file name="calendar.png" server="mayan-capital.com" local="130055691460000000" remote="131326317000000000" Dst="1" />
<file name="client.png" server="mayan-capital.com" local="130055691460000000" remote="131326317000000000" Dst="1" />
<file name="dashboard.png" server="mayan-capital.com" local="130055691460000000" remote="131326317000000000" Dst="1" />
<file name="database.png" server="mayan-capital.com" local="130055691460000000" remote="131326317000000000" Dst="1" />
<file name="download.png" server="mayan-capital.com" local="130055691460000000" remote="131326317000000000" Dst="1" />
<file name="graph.png" server="mayan-capital.com" local="130055691460000000" remote="131326317000000000" Dst="1" />
<file name="home.png" server="mayan-capital.com" local="130055691460000000" remote="131326317000000000" Dst="1" />
<file name="lock.png" server="mayan-capital.com" local="130055691460000000" remote="131326317000000000" Dst="1" />
<file name="mail.png" server="mayan-capital.com" local="130055691460000000" remote="131326317000000000" Dst="1" />
<file name="pdf.png" server="mayan-capital.com" local="130055691460000000" remote="131326317000000000" Dst="1" />
<file name="piechart.png" server="mayan-capital.com" local="130055691460000000" remote="131326317000000000" Dst="1" />
<file name="search.png" server="mayan-capital.com" local="130055691460000000" remote="131326317000000000" Dst="1" />
<file name="shopping-bag.png" server="mayan-capital.com" local="130055691480000000" remote="131326317000000000" Dst="1" />
<file name="people.png" server="mayan-capital.com" local="130055691460000000" remote="131326317000000000" Dst="1" />
<file name="wallet.png" server="mayan-capital.com" local="130055691480000000" remote="131326317000000000" Dst="1" />
<file name="web.png" server="mayan-capital.com" local="130055691480000000" remote="131326317000000000" Dst="1" />
<file name="tag.png" server="mayan-capital.com" local="130055691480000000" remote="131326317000000000" Dst="1" />
<file name="user.png" server="mayan-capital.com" local="130055691480000000" remote="131326317000000000" Dst="1" />
<file name="survey.png" server="mayan-capital.com" local="130055691480000000" remote="131326317000000000" Dst="1" />
<file name="Thumbs.db" server="mayan-capital.com" local="130055691480000000" remote="131326317000000000" Dst="1" />
</dwsync>